{
    "enter_camp" : {
        "type": "enter_camp",
        "command" : "!camp",
        "status": 1,
        "user_level": [
              "moderador"
        ],
        "delay": "5",
        "last_use": 0,
        "cost" : 0,
        "cost_status" : 0,
        "whitelist_status" : 0,
        "whitelist": [],
        "blacklist": []
    },   
    "add_camp" : {
        "type": "add_camp",
        "command" : "!addcamp",
        "status": 1,
        "user_level": [
              "moderador"
        ],
        "delay": "5",
        "last_use": 0,
        "cost" : 0,
        "cost_status" : 0,
        "whitelist_status" : 0,
        "whitelist": [],
        "blacklist": []
    },   
    "remove_camp" : {
        "type": "remove_camp",
        "command" : "!removecamp",
        "status": 1,
        "user_level": [
              "moderador"
        ],
        "delay": "5",
        "last_use": 0,
        "cost" : 0,
        "cost_status" : 0,
        "whitelist_status" : 0,
        "whitelist": [],
        "blacklist": []
    }
}

